pggm_mcp_snowflake_server/__init__.py
pggm_mcp_snowflake_server/server.py
pggm_mcp_snowflake_server/write_detector.py
pggm_mcp_snowflake_server-1.0.7.dist-info/METADATA
pggm_mcp_snowflake_server-1.0.7.dist-info/WHEEL
pggm_mcp_snowflake_server-1.0.7.dist-info/entry_points.txt
pggm_mcp_snowflake_server-1.0.7.dist-info/top_level.txt
pggm_mcp_snowflake_server-1.0.7.dist-info/RECORD
