Metadata-Version: 2.4
Name: pggm-mcp-snowflake-server
Version: 1.0.7
Summary: Custom Model Context Protocol server for Snowflake
Classifier: Programming Language :: Python :: 3
Classifier: License :: OSI Approved :: MIT License
Classifier: Operating System :: OS Independent
Requires-Python: >=3.8
Requires-Dist: mcp
Requires-Dist: pydantic
Requires-Dist: snowflake-snowpark-python
Requires-Dist: pyyaml
Requires-Dist: jaraco.text
